pwhl_api/__init__.py
pwhl_api/endpoints/__init__.py
pwhl_api/endpoints/gamepreview.py
pwhl_api/endpoints/gamesummary.py
pwhl_api/endpoints/leagueschedule.py
pwhl_api/endpoints/leaguestandings.py
pwhl_api/endpoints/playbyplay.py
pwhl_api/endpoints/playercareerstats.py
pwhl_api/endpoints/playergoaliestats.py
pwhl_api/endpoints/playerleagueleaders.py
pwhl_api/endpoints/playerskaterstats.py
pwhl_api/endpoints/teamroster.py
pwhl_api/endpoints/library/__init__.py
pwhl_api/endpoints/library/http.py
pwhl_api/library/__init__.py
pwhl_api/library/http.py
pwhl_api/static/__init__.py
pwhl_api/static/players.json
pwhl_api/static/players.py
pwhl_api/static/seasons.json
pwhl_api/static/seasons.py
pwhl_api/static/teams.json
pwhl_api/static/teams.py
pwhl_api-0.1.2.dist-info/licenses/LICENSE
pwhl_api-0.1.2.dist-info/METADATA
pwhl_api-0.1.2.dist-info/WHEEL
pwhl_api-0.1.2.dist-info/top_level.txt
pwhl_api-0.1.2.dist-info/RECORD
