Metadata-Version: 2.4
Name: pwhl_api
Version: 0.1.2
Summary: An API Client package to access the APIs for thepwhl.com
Author-email: Mason Langer <masonelanger@gmail.com>
Maintainer-email: Mason Langer <masonelanger@gmail.com>
License-Expression: MIT
Project-URL: Homepage, https://github.com/masonlanger/pwhl_api
Project-URL: Issues, https://github.com/masonlanger/pwhl_api/issues
Keywords: api,hockey,data,pwhl,sports,stats
Requires-Python: >=3.10
License-File: LICENSE
Requires-Dist: numpy>=1.26.0; python_version < "3.13"
Requires-Dist: numpy>=2.1.0; python_version >= "3.13"
Requires-Dist: pandas>=2.1.0; python_version < "3.12"
Requires-Dist: pandas>=2.2.0; python_version >= "3.12"
Requires-Dist: requests<3.0.0,>=2.32.3
Dynamic: license-file
